{
    "cuda": true,
    "multigpu": false,
    "KMP_DUPLICATE_LIB_OK": true,
    "output": "models/L1/Aq_Z=1_bs=2048_ross",
    "mixed": false,
    "batch_size": 2048,
    "training_frac": 0.8,
    "ds": "../BuildDataset/AqZ=1_rmsd=2.h5",
    "valds": null,
    "hard_reset": false,
    "log": "Log.txt",
    "logfile": "Training.log",
    "model_n": 1,
    "reset_lr": false,
    "fc": 0.0,
    "GraphEveryEpoch": 10,
    "HasForces": false,
    "lr": 0.001,
    "preLoadANI": false,
    "preLoadANI_model_path": "ANIWEIGHTS/ani-2x_8x/train0/networks",
    "early_stop": 0.1,
    "early_stopping_learning_rate": 1e-05,
    "Rcr": 5.2,
    "Rca": 3.5,
    "remove_self_energy": true,
    "preAEV": false,
    "sigmoid": false,
    "celu0": 0.1,
    "celu1": 0.1,
    "L1": true,
    "Stratified": false,
    "TrainDS": null,
    "TestDS": null,
    "species_order": [
        "H",
        "C",
        "N",
        "O",
        "Cl"
    ],
    "random_seed": 1703028687,
    "cmd": "--cuda --output models/L1/Aq_Z=1_bs=2048_ross --batch_size 2048 --ds ../BuildDataset/AqZ=1_rmsd=2.h5 --lr 0.001 --remove_self_energy --celu0 0.1 --celu1 0.1 --Rcr 5.2 --Rca 3.5 --hard_reset --training_frac 0.8 --L1",
    "aev_dim": 560,
    "Max": null,
    "Min": null
}